optoid/__init__.py
optoid/commander.py
optoid/find_window.py
optoid/window_title.py
optoid-0.2.0.dist-info/METADATA
optoid-0.2.0.dist-info/WHEEL
optoid-0.2.0.dist-info/top_level.txt
optoid-0.2.0.dist-info/RECORD
