Metadata-Version: 2.1
Name: optoid
Version: 0.2.0
Summary: A helper tool named optoid.
Author: Ryusuke Narita
Author-email: ryusukenarita2718@gmail.com
License: MIT
Requires-Dist: dependency1
Requires-Dist: dependency2 (>=1.0)
Requires-Dist: dependency3 (<2.0)
